LICENSE
MANIFEST.in
README.md
setup.py
streamlit_js_callback/__init__.py
streamlit_js_callback/example.py
streamlit_js_callback.egg-info/PKG-INFO
streamlit_js_callback.egg-info/SOURCES.txt
streamlit_js_callback.egg-info/dependency_links.txt
streamlit_js_callback.egg-info/requires.txt
streamlit_js_callback.egg-info/top_level.txt
streamlit_js_callback/frontend/build/asset-manifest.json
streamlit_js_callback/frontend/build/bootstrap.min.css
streamlit_js_callback/frontend/build/index.html
streamlit_js_callback/frontend/build/static/js/main.1762ab43.js
streamlit_js_callback/frontend/build/static/js/main.1762ab43.js.LICENSE.txt
streamlit_js_callback/frontend/build/static/js/main.1762ab43.js.map