Metadata-Version: 2.1
Name: streamlit-js-callback
Version: 1.0.1
Summary: Eval js code with callbaack
Home-page: https://github.com/dancingpeanut/streamlit-js-callback
Author: Tongshengzhou
Author-email: tongshengzhou@gmail.com
Requires-Python: >=3.7
Provides-Extra: devel
License-File: LICENSE
